decc/__init__.py
decc/benchmark/__init__.py
decc/benchmark/ackley.py
decc/benchmark/sphere.py
decc/core/__init__.py
decc/core/optimizer.py
decc/core/problem.py
decc/decomposition/__init__.py
decc/operators/__init__.py
decc/operators/crossover.py
decc/operators/mutation.py
decc/operators/neighborhood_search.py
decc/operators/selection.py
decc/optimizers/__init__.py
decc/optimizers/decc.py
decc/optimizers/decc_g.py
decc/utils/__init__.py
decc/utils/classic_de.py
decc/utils/sansde.py
decc-0.2.3.dist-info/LICENSE
decc-0.2.3.dist-info/METADATA
decc-0.2.3.dist-info/WHEEL
decc-0.2.3.dist-info/top_level.txt
decc-0.2.3.dist-info/RECORD
