Metadata-Version: 2.1
Name: decc
Version: 0.2.3
Summary: Cooperative Co-evolutionary Differential Evolution algorithms in Python.
Project-URL: Github, https://github.com/moesio-f/decc
Keywords: decc
Classifier: Development Status :: 3 - Alpha
Classifier: Intended Audience :: Developers
Classifier: Natural Language :: English
Classifier: Programming Language :: Python :: 3.8
Classifier: Programming Language :: Python :: 3.9
Classifier: Programming Language :: Python :: 3.10
Requires-Python: >=3.8
License-File: LICENSE
Requires-Dist: numpy >=1.23
